Metadata-Version: 2.1
Name: talentlms
Version: 1.0.1
Summary: TalentLMS API Python library
Home-page: https://github.com/ib1984/py-talentlms
Author: Ivan Butorin
Author-email: ibutorin@plesk.com
License: MIT
Platform: UNKNOWN
Classifier: Programming Language :: Python :: 2.7
Classifier: Programming Language :: Python :: 3
Classifier: Operating System :: OS Independent
Classifier: License :: OSI Approved :: MIT License
Classifier: Topic :: Software Development :: Libraries
Classifier: Intended Audience :: Developers
Classifier: Intended Audience :: Information Technology
Requires-Python: >=2.7
